textchat/__init__.py
textchat/client.py
textchat/irc.tcss
textchat/ircchat.py
textchat/commands/__init__.py
textchat/db/__init__.py
textchat/db/base.py
textchat/db/db.py
textchat/db/model.py
textchat/screens/__init__.py
textchat/screens/irc.py
textchat/screens/quit.py
textchat/screens/settings.py
textchat/screens/whois.py
textchat/utils/channels.py
textchat/widgets/__init__.py
textchat/widgets/address.py
textchat/widgets/channel_list.py
textchat/widgets/channels.py
textchat/widgets/channeltree.py
textchat/widgets/input.py
textchat/widgets/nickname.py
textchat/widgets/password.py
textchat-0.1.9.dist-info/LICENSE.md
textchat-0.1.9.dist-info/METADATA
textchat-0.1.9.dist-info/WHEEL
textchat-0.1.9.dist-info/entry_points.txt
textchat-0.1.9.dist-info/top_level.txt
textchat-0.1.9.dist-info/RECORD
