Metadata-Version: 2.1
Name: textchat
Version: 0.1.9
Author-email: Matthew Blau <mrb1105@gmail.com>
Classifier: Programming Language :: Python :: 3
Classifier: License :: OSI Approved :: MIT License
Requires-Python: >=3.8
License-File: LICENSE.md
Requires-Dist: textual >=0.76.0
Requires-Dist: irc >=20.4.3
Requires-Dist: textual-autocomplete >=2.1.0b0
Requires-Dist: SQLAlchemy >=2.0.30
Requires-Dist: aiosqlite >=0.20.0
